build/lib/cognitive_space/__init__.py
build/lib/cognitive_space/algorithms/__init__.py
build/lib/cognitive_space/algorithms/cognitive_encode.py
build/lib/cognitive_space/algorithms/cognitive_recall.py
build/lib/cognitive_space/algorithms/cognitive_synthesis.py
build/lib/cognitive_space/algorithms/embedding_model/__init__.py
build/lib/cognitive_space/algorithms/embedding_model/embedding_encode.py
build/lib/cognitive_space/algorithms/embedding_model/emdedding_recall.py
build/lib/cognitive_space/algorithms/gravitational_model/__init__.py
build/lib/cognitive_space/algorithms/gravitational_model/gravitational_encode.py
build/lib/cognitive_space/algorithms/gravitational_model/gravitational_recall.py
build/lib/cognitive_space/brain/__init__.py
build/lib/cognitive_space/brain/brain.py
build/lib/cognitive_space/storage/__init__.py
build/lib/cognitive_space/storage/storage_layer.py
build/lib/cognitive_space/storage/azure_ai_search/__init__.py
build/lib/cognitive_space/storage/azure_ai_search/azure_ai_search_storage.py
build/lib/cognitive_space/storage/mongo/mongo_storage.py
build/lib/cognitive_space/tool_builder/__init__.py
build/lib/cognitive_space/tool_builder/cognitive_encoder_tool.py
build/lib/cognitive_space/tool_builder/cognitive_recall_tool.py
cognitive_space/__init__.py
cognitive_space/algorithms/__init__.py
cognitive_space/algorithms/cognitive_encode.py
cognitive_space/algorithms/cognitive_recall.py
cognitive_space/algorithms/cognitive_synthesis.py
cognitive_space/algorithms/embedding_model/__init__.py
cognitive_space/algorithms/embedding_model/embedding_encode.py
cognitive_space/algorithms/embedding_model/emdedding_recall.py
cognitive_space/algorithms/gravitational_model/__init__.py
cognitive_space/algorithms/gravitational_model/gravitational_encode.py
cognitive_space/algorithms/gravitational_model/gravitational_recall.py
cognitive_space/brain/__init__.py
cognitive_space/brain/brain.py
cognitive_space/storage/__init__.py
cognitive_space/storage/storage_layer.py
cognitive_space-0.0.1.dist-info/LICENSE
cognitive_space-0.0.1.dist-info/METADATA
cognitive_space-0.0.1.dist-info/WHEEL
cognitive_space-0.0.1.dist-info/top_level.txt
cognitive_space-0.0.1.dist-info/RECORD
